DESIGN/RTL/mux/alusrcb_mux.v
/*
==============================================================================
 Project      : RV32I Multi-Cycle RISC-V Processor
 Module No    : M15
 Module Name  : alusrcb_mux
 File Name    : alusrcb_mux.v

 Core         : RV32I
 Architecture : Multi-Cycle
 ISA          : RV32I Base Integer ISA
 XLEN         : 32-bit

 Description  : Selects the second operand for the ALU.

 Date Created : 06.07.2026
 Version      :

 Inputs       : B_out, constant_4, ImmExt, ALUSrcB

 Outputs      : alu_src_b

==============================================================================
*/

module alusrcb_mux(B_out, ImmExt, ALUSrcB, alu_src_b);
	
	input [31:0] B_out, ImmExt;
	input [1:0] ALUSrcB;
	
	output reg [31:0] alu_src_b;
	
	always @ (*)
		begin
			case(ALUSrcB)
				2'b00 : alu_src_b = B_out;
				2'b01 : alu_src_b = 32'd4;
				2'b10 : alu_src_b = ImmExt;
			    default : alu_src_b = 32'b00;
			endcase
		end
 
endmodule

DESIGN/TEST_BENCH/mux_tb/alusrcb_mux_tb.v
module alusrcb_mux_tb;

	reg [31:0] B_out,ImmExt;
	reg [1:0] ALUSrcB;
	
	wire [31:0] alu_src_b;
	
	alusrcb_mux uut (B_out, ImmExt, ALUSrcB, alu_src_b);
	integer seed = 100;
	integer seed1 = 200;
    integer seed2 = 300;
	
	task stimulus ;
	begin
		repeat(20)
		begin
            #10;
			B_out    = $urandom(seed1);
            ImmExt   = $urandom(seed2);
			ALUSrcB  = $urandom %4;
            #1;
			
			$display("-----------------------");
            $display("B_out == %0d",B_out);
			$display("constant_4 == %0d",32'd4);
			$display("ImmExt == %0d",ImmExt);
            $display("ALUSrcB == %0d",ALUSrcB);
			#1;
			if(ALUSrcB == 2'b00)
			begin
				if(B_out == alu_src_b)
                begin
                $display("alu_src_b == %0d",alu_src_b);
				$display("b_out is selected");
                end
				else
				begin
				$display("b_out is not selected correctly");
				$stop;
				end
			end
			
			
			else if (ALUSrcB == 2'b01)
			begin
				if(alu_src_b == 32'd4)
                begin
                $display("alu_src_b == %0d",alu_src_b);
				$display("constant_4 is selected");
                end
				else
				begin
				$display("constant_4 is not selected correctly");
				$stop;
				end
			end
			
			else if (ALUSrcB == 2'b10)
			begin
				if(alu_src_b == ImmExt)
                begin
                $display("ImmExt == %0d",ImmExt);
				$display("ImmExt is selected");
                end
				else
				begin
				$display("ImmExt is not selected correctly");
				$stop;
				end
			end
			
			else 
			begin
				if(alu_src_b == 32'b00 )
                begin
                $display("alu_src_b == %0d",alu_src_b);
				$display("zero is displayed");
                end
				else
				begin
				$display("zero is not displayed");
				$stop;
				end
			end
			
			
		end
	end
    endtask
	
	initial
	begin
		ImmExt = 0;
		B_out =0;
		ALUSrcB =2'b01;
        #1;
            $display("-----------------------");
            $display("B_out == %0d",B_out);
			$display("constant_4 == %0d",32'd4);
			$display("ImmExt == %0d",ImmExt);
            $display("ALUSrcB == %0d",ALUSrcB);
			
			
            if(ALUSrcB == 2'b00)
			begin
				if(B_out == alu_src_b)
                begin
                $display("alu_src_b == %0d",alu_src_b);
				$display("b_out is selected");
                end
				else
				begin
				$display("b_out is not selected correctly");
				$stop;
				end
			end
			
			
			else if (ALUSrcB == 2'b01)
			begin
				if(alu_src_b == 32'd4)
                begin
                $display("alu_src_b == %0d",alu_src_b);
				$display("constant_4 is selected");
                end
				else
				begin
				$display("constant_4 is not selected correctly");
				$stop;
				end
			end
			
			else if (ALUSrcB == 2'b10)
			begin
				if(alu_src_b == ImmExt)
                begin
                $display("ImmExt == %0d",ImmExt);
				$display("ImmExt is selected");
                end
				else
				begin
				$display("ImmExt is not selected correctly");
				$stop;
				end
			end
			
			else 
			begin
				if(alu_src_b == 32'b00 )
                begin
                $display("alu_src_b == %0d",alu_src_b);
				$display("zero is displayed");
                end
				else
				begin
				$display("zero is not displayed");
				$stop;
				end
			end

		stimulus;
		#10;
        $finish;

	end

	initial begin
		$dumpfile("SIM/alusrcb_mux.vcd");
		$dumpvars(0,alusrcb_mux_tb);
	end
endmodule

DESIGN/SIM/alusrcb_mux.vcd
$date
	Mon Jul 13 18:00:46 2026
$end
$version
	Icarus Verilog
$end
$timescale
	1s
$end
$scope module alusrcb_mux_tb $end
$var wire 32 ! alu_src_b [31:0] $end
$var reg 2 " ALUSrcB [1:0] $end
$var reg 32 # B_out [31:0] $end
$var reg 32 $ ImmExt [31:0] $end
$var integer 32 % seed [31:0] $end
$var integer 32 & seed1 [31:0] $end
$var integer 32 ' seed2 [31:0] $end
$scope module uut $end
$var wire 2 ( ALUSrcB [1:0] $end
$var wire 32 ) B_out [31:0] $end
$var wire 32 * ImmExt [31:0] $end
$var reg 32 + alu_src_b [31:0] $end
$upscope $end
$scope task stimulus $end
$upscope $end
$upscope $end
$enddefinitions $end
$comment Show the parameter values. $end
$dumpall
$end
#0
$dumpvars
b100 +
b0 *
b0 )
b1 (
b100101100 '
b11001000 &
b1100100 %
b0 $
b0 #
b1 "
b100 !
$end
#11
b0 !
b0 +
b11 "
b11 (
b1001111000010111000000010 $
b1001111000010111000000010 *
b1001111000010110000111101 '
b110100101100101000000001 #
b110100101100101000000001 )
b110100101100100000101001 &
#23
b100101000111010101111001001010 !
b100101000111010101111001001010 +
b0 "
b0 (
b110111101010111000011001101111 $
b110111101010111000011001101111 *
b110111101010111000010111011010 '
b100101000111010101111001001010 #
b100101000111010101111001001010 )
b100101000111010101110111010110 &
#35
b11010000000000000100001110100000 !
b11010000000000000100001110100000 +
b10 "
b10 (
b11010000000000000100001110100000 $
b11010000000000000100001110100000 *
b11010000000000000100000110010011 '
b10010100000111100000010100101000 #
b10010100000111100000010100101000 )
b10010100000111100000001001011111 &
#47
b100 !
b100 +
b1 "
b1 (
b11010101000110111111101110101010 $
b11010101000110111111101110101010 *
b11010101000110111111100110111000 '
b100100100001011011101001001001 #
b100100100001011011101001001001 )
b100100100001011011100100010100 &
#59
b0 !
b0 +
b11 "
b11 (
b1100110011010101001000011001 $
b1100110011010101001000011001 *
b1100110011010101000001011001 '
b11000010100011110011101110000101 #
b11000010100011110011101110000101 )
b11000010100011110011100100000101 &
#71
b100 !
b100 +
b1 "
b1 (
b11111101110101101101111111111011 $
b11111101110101101101111111111011 *
b11111101110101101101110001000110 '
b1001011100110101110110010010111 #
b1001011100110101110110010010111 )
b1001011100110101110101000000010 &
#83
b1010100000111111010000010101 !
b1010100000111111010000010101 +
b10 "
b10 (
b1010100000111111010000010101 $
b1010100000111111010000010101 *
b1010100000111111001000001111 '
b1010010111100010111111010100101 #
b1010010111100010111111010100101 )
b1010010111100010111110110011011 &
#95
b0 !
b0 +
b11 "
b11 (
b10001000000101001101000100010 $
b10001000000101001101000100010 *
b10001000000101001100100000100 '
b101100010111010111011001011000 #
b101100010111010111011001011000 )
b101100010111010111010000100000 &
#107
b1011001110111011011111010110011 !
b1011001110111011011111010110011 +
b10 "
b10 (
b1011001110111011011111010110011 $
b1011001110111011011111010110011 *
b1011001110111011011110000110101 '
b10111001110110111001111101110011 #
b10111001110110111001111101110011 )
b10111001110110111001110110100001 &
#119
b11110101010100110110100111101010 !
b11110101010100110110100111101010 +
b11110101010100110110100111101010 $
b11110101010100110110100111101010 *
b11110101010100110110011101110010 '
b10011001011111110110100100110010 #
b10011001011111110110100100110010 )
b10011001011111110110011011101110 &
#131
b10111011111001010001000101110 !
b10111011111001010001000101110 +
b10111011111001010001000101110 $
b10111011111001010001000101110 *
b10111011111001010000001001011 '
b11001010001011011000010110010100 #
b11001010001011011000010110010100 )
b11001010001011011000001010010111 &
#143
b100 !
b100 +
b1 "
b1 (
b11000011001110110010110110000110 $
b11000011001110110010110110000110 *
b11000011001110110010101100010000 '
b10111000101010100011111101110001 #
b10111000101010100011111101110001 )
b10111000101010100011110111101100 &
#155
b0 !
b0 +
b11 "
b11 (
b10000010101000010100110100000101 $
b10000010101000010100110100000101 *
b10000010101000010100101111010001 '
b11000011011001001001001110000110 #
b11000011011001001001001110000110 )
b11000011011001001001000111111101 &
#167
b100 !
b100 +
b1 "
b1 (
b10111110101000101010000101111 $
b10111110101000101010000101111 *
b10111110101000101001101011110 '
b100100111011111100001001001001 #
b100100111011111100001001001001 )
b100100111011111100000010011010 &
#179
b0 !
b0 +
b11 "
b11 (
b110000101000001000101001100001 $
b110000101000001000101001100001 *
b110000101000001000100001000111 '
b10000001010111110000111100000010 #
b10000001010111110000111100000010 )
b10000001010111110000110101010011 &
#191
b100 !
b100 +
b1 "
b1 (
b10011111101111111011110100111111 $
b10011111101111111011110100111111 *
b10011111101111111011101111011100 '
b1111010000111011110010011110100 #
b1111010000111011110010011110100 )
b1111010000111011110001001111000 &
#203
b0 !
b0 +
b11 "
b11 (
b1100100111011111001110011001001 $
b1100100111011111001110011001001 *
b1100100111011111001101100101101 '
b110000111001100111010001100001 #
b110000111001100111010001100001 )
b110000111001100111001000011001 &
#215
b10011001111011011000111100110011 !
b10011001111011011000111100110011 +
b10 "
b10 (
b10011001111011011000111100110011 $
b10011001111011011000111100110011 *
b10011001111011011000110000001010 '
b1001110011011011010010010011100 #
b1001110011011011010010010011100 )
b1001110011011011010001100000110 &
#227
b11011111010111111010100110111110 !
b11011111010111111010100110111110 +
b11011111010111111010100110111110 $
b11011111010111111010100110111110 *
b11011111010111111010011000000011 '
b10000110001101101000000100 #
b10000110001101101000000100 )
b10000110001101100111001111 &
#239
b0 !
b0 +
b11 "
b11 (
b1100001000010010001100011000010 $
b1100001000010010001100011000010 *
b1100001000010010001011101101000 '
b11001010110001001110111110010101 #
b11001010110001001110111110010101 )
b11001010110001001110110111000100 &
