DESIGN/RTL/datapath/imm_gen.v
/*
==============================================================================
 Project      : RV32I Multi-Cycle RISC-V Processor
 Module No    : M8
 Module Name  : imm_gen
 File Name    : imm_gen.v

 Core         : RV32I
 Architecture : Multi-Cycle
 ISA          : RV32I Base Integer ISA
 XLEN         : 32-bit

 Description  : The Immediate Generator (ImmGen) extracts the immediate field from the current instruction stored in the Instruction Register 
				(IR) and generates a 32-bit immediate value according to the RV32I instruction format.

 Date Created : 07.07.2026
 Version      :

 Inputs       : instruction

 Outputs      : ImmExt

==============================================================================
*/

module imm_gen(instruction,ImmExt);
	
	input [31:0] instruction;
	output reg [31:0] ImmExt;
	
	always @(*)
		case (instruction[6:0])
			
			// I - type
			7'b0010011, 7'b0000011, 7'b1100111 : ImmExt = {{20{instruction[31]}}, instruction[31:20]};
	
			// S - type 
			7'b0100011 : ImmExt = {{20{instruction[31]}}, instruction[31:25], instruction[11:7]};
			
			// B - type 
			7'b1100011 : ImmExt = {{19{instruction[31]}}, instruction[31], instruction[7], instruction[30:25], instruction[11:8], 1'b0};
			
			// U - type 
			7'b0110111, 7'b0010111 : ImmExt = {instruction[31:12], 12'd0};
			
			// J - type  (JAL)
			7'b1101111 : ImmExt = {{11{instruction[31]}}, instruction[31], instruction[19:12], instruction[20], instruction[30:21], 1'b0};
			
			default    : ImmExt = 32'd0;
		
		endcase 

endmodule

DESIGN/TEST_BENCH/datapath_tb/immediate_gen_tb.v
module immediate_generator_tb ;
	reg [31:0] instruction;
	wire [31:0] imm;
	
	imm_gen uut (instruction,imm);
	
	function [31:0] expected_imm;
		input [31:0] instr;
		reg [6:0] opcode;
	begin
		opcode = instr[6:0];
		
		case(opcode)
			7'b0010011,
			7'b0000011,
			7'b1100111 : expected_imm = {{20{instr[31]}},instr[31:20]};
			7'b0100011 : expected_imm = {{20{instr[31]}},instr[31:25],instr[11:7]};
			7'b1100011 : expected_imm = {{19{instr[31]}},instr[31],instr[7],instr[30:25],instr[11:8],1'b0};
			7'b0110111,
			7'b0010111 : expected_imm = {instr[31:12],12'd0};
			7'b1101111 : expected_imm = {{11{instr[31]}},instr[31],instr[19:12],instr[20],instr[30:21],1'b0};
			default    : expected_imm = 32'd0; 
		endcase
	end
	endfunction
	
	integer error_count;
	integer test_count;
	
	task check_imm ;
	input [31:0]instr;
	input [30*8:1] text_name ;
	reg [31:0] expected  ;
	begin
		instruction = instr;
		#1;
		expected =  expected_imm(instr);
		test_count = test_count +1;
		
		if(expected == imm)
			$display("passed [%0s] instr = %0h expected = %0h imm = %0h",text_name,instr,expected,imm);
		else
		begin
			$display("failed [%0s] instr = %0h expected = %0h imm = %0h",text_name,instr,expected,imm);
			error_count = error_count+1;
		end
	end
	endtask
	
	
	task directed_tests ;
	begin
		check_imm({12'd5,5'd8,3'd0,5'd1,7'b0010011},"I type positive");
		check_imm({12'd8,5'd3,3'd2,5'd2,7'b0000011},"lw positive");
		check_imm({12'd8,5'd5,3'd0,5'd1,7'b1100111},"jalr positive");
		check_imm({7'd0,5'd8,5'd1,3'd2,5'd8,7'b0100011},"sw positive");
		check_imm({1'b0,6'd0,5'd2,5'd1,3'd0,4'd4,1'b0,7'b1100011}, "B-type positive (BEQ)");
		check_imm({20'h12345, 5'd1, 7'b0110111}, "U-type (LUI)");
		check_imm({20'hFFFFF, 5'd1, 7'b0010111}, "U-type (AUIPC, all 1s)");
		check_imm({1'b0,10'd8,1'b0,8'd0,5'd1,7'b1101111}, "J-type positive (JAL)");
		check_imm({7'd0,5'd8,5'd6,3'd0,5'd5,7'b0110011},"R-type positive");
	end
	endtask
	
	
	task random;
	 integer i;
	 reg [6:0] valid_opcodes [0:5];
	 reg [31:0] instr;
        begin
            valid_opcodes[0] = 7'b0010011; // I-type (ADDI etc.)
            valid_opcodes[1] = 7'b0000011; // I-type (loads)
            valid_opcodes[2] = 7'b1100111; // I-type (JALR)
            valid_opcodes[3] = 7'b0100011; // S-type
            valid_opcodes[4] = 7'b1100011; // B-type
            valid_opcodes[5] = 7'b1101111; // J-type
			
	        for(i=0;i<40;i = i+1)
			begin
				instr = $urandom;
				instr[6:0] = valid_opcodes[{$random}%6];
				check_imm(instr,"RANDOM");
			end
		end
	endtask
	
	initial begin
		error_count = 0;
		test_count = 0;
		
		directed_tests;
		random;
		
	    $display("--------------------------------------------------");
        $display("TESTS RUN   : %0d", test_count);
        $display("TESTS FAILED: %0d", error_count);
		if(error_count == 0)
		
			$display("ALL test case passes");
		else
			$display("test case failed with error of %0d ",error_count);
		$finish;
	end
	
	initial begin
		$dumpfile("SIM/imm.vcd");
		$dumpvars(0,immediate_generator_tb);
	end
endmodule

DESIGN/SIM/imm.vcd
$date
	Tue Jul 21 22:06:55 2026
$end
$version
	Icarus Verilog
$end
$timescale
	1s
$end
$scope module immediate_generator_tb $end
$var wire 32 ! imm [31:0] $end
$var reg 32 " instruction [31:0] $end
$var integer 32 # error_count [31:0] $end
$var integer 32 $ test_count [31:0] $end
$scope function expected_imm $end
$var reg 32 % instr [31:0] $end
$var reg 7 & opcode [6:0] $end
$upscope $end
$scope module uut $end
$var wire 32 ' instruction [31:0] $end
$var reg 32 ( ImmExt [31:0] $end
$upscope $end
$scope task check_imm $end
$var reg 32 ) expected [31:0] $end
$var reg 32 * instr [31:0] $end
$var reg 240 + text_name [240:1] $end
$upscope $end
$scope task directed_tests $end
$upscope $end
$scope task random $end
$var reg 32 , instr [31:0] $end
$var integer 32 - i [31:0] $end
$upscope $end
$upscope $end
$enddefinitions $end
$comment Show the parameter values. $end
$dumpall
$end
#0
$dumpvars
bx -
bx ,
b10010010010000001110100011110010111000001100101001000000111000001101111011100110110100101110100011010010111011001100101 +
b10101000000000010010011 *
bx )
b101 (
b10101000000000010010011 '
bx &
bx %
b0 $
b0 #
b10101000000000010010011 "
b101 !
$end
#1
b1000 !
b1000 (
b100000011010000100000011 "
b100000011010000100000011 '
b110110001110111001000000111000001101111011100110110100101110100011010010111011001100101 +
b100000011010000100000011 *
b1 $
b101 )
b10011 &
b10101000000000010010011 %
#2
b100000101000000011100111 "
b100000101000000011100111 '
b1101010011000010110110001110010001000000111000001101111011100110110100101110100011010010111011001100101 +
b100000101000000011100111 *
b10 $
b1000 )
b11 &
b100000011010000100000011 %
#3
b100000001010010000100011 "
b100000001010010000100011 '
b111001101110111001000000111000001101111011100110110100101110100011010010111011001100101 +
b100000001010010000100011 *
b11 $
b1100111 &
b100000101000000011100111 %
#4
b1000001000010001100011 "
b1000001000010001100011 '
b10000100010110101110100011110010111000001100101001000000111000001101111011100110110100101110100011010010111011001100101001000000010100001000010010001010101000100101001 +
b1000001000010001100011 *
b100 $
b100011 &
b100000001010010000100011 %
#5
b10010001101000101000000000000 !
b10010001101000101000000000000 (
b10010001101000101000010110111 "
b10010001101000101000010110111 '
b10101010010110101110100011110010111000001100101001000000010100001001100010101010100100100101001 +
b10010001101000101000010110111 *
b101 $
b1100011 &
b1000001000010001100011 %
#6
b11111111111111111111000000000000 !
b11111111111111111111000000000000 (
b11111111111111111111000010010111 "
b11111111111111111111000010010111 '
b1010101001011010111010001111001011100000110010100100000001010000100000101010101010010010101000001000011001011000010000001100001011011000110110000100000001100010111001100101001 +
b11111111111111111111000010010111 *
b110 $
b10010001101000101000000000000 )
b110111 &
b10010001101000101000010110111 %
#7
b10000 !
b10000 (
b1000000000000000011101111 "
b1000000000000000011101111 '
b10010100010110101110100011110010111000001100101001000000111000001101111011100110110100101110100011010010111011001100101001000000010100001001010010000010100110000101001 +
b1000000000000000011101111 *
b111 $
b11111111111111111111000000000000 )
b10111 &
b11111111111111111111000010010111 %
#8
b0 !
b0 (
b100000110000001010110011 "
b100000110000001010110011 '
b10100100010110101110100011110010111000001100101001000000111000001101111011100110110100101110100011010010111011001100101 +
b100000110000001010110011 *
b1000 $
b10000 )
b1101111 &
b1000000000000000011101111 %
#9
b11111111111111111111100100100001 !
b11111111111111111111100100100001 (
b10010010000101010011010101100111 "
b10010010000101010011010101100111 '
b10100100100000101001110010001000100111101001101 +
b10010010000101010011010101100111 *
b10010010000101010011010101100111 ,
b0 -
b1001 $
b0 )
b110011 &
b100000110000001010110011 %
#10
b10000011101 !
b10000011101 (
b1000000100010010101111010100011 "
b1000000100010010101111010100011 '
b1000000100010010101111010100011 *
b1000000100010010101111010100011 ,
b1 -
b1010 $
b11111111111111111111100100100001 )
b1100111 &
b10010010000101010011010101100111 %
#11
b1001000 !
b1001000 (
b100100001001101011000000011 "
b100100001001101011000000011 '
b100100001001101011000000011 *
b100100001001101011000000011 ,
b10 -
b1011 $
b10000011101 )
b100011 &
b1000000100010010101111010100011 %
#12
b101101100011110 !
b101101100011110 (
b110001111100000101011001101111 "
b110001111100000101011001101111 '
b110001111100000101011001101111 *
b110001111100000101011001101111 ,
b11 -
b1100 $
b1001000 )
b11 &
b100100001001101011000000011 %
#13
b11111111111111111111100001110110 !
b11111111111111111111100001110110 (
b10000110101110010111101100100011 "
b10000110101110010111101100100011 '
b10000110101110010111101100100011 *
b10000110101110010111101100100011 ,
b100 -
b1101 $
b101101100011110 )
b1101111 &
b110001111100000101011001101111 %
#14
b11111111111111111001110001101100 !
b11111111111111111001110001101100 (
b11000110110111111001100111101111 "
b11000110110111111001100111101111 '
b11000110110111111001100111101111 *
b11000110110111111001100111101111 ,
b101 -
b1110 $
b11111111111111111111100001110110 )
b100011 &
b10000110101110010111101100100011 %
#15
b101000001100101100 !
b101000001100101100 (
b110010110000101000010001101111 "
b110010110000101000010001101111 '
b110010110000101000010001101111 *
b110010110000101000010001101111 ,
b110 -
b1111 $
b11111111111111111001110001101100 )
b1101111 &
b11000110110111111001100111101111 %
#16
b10000100 !
b10000100 (
b1001001101110101001001100011 "
b1001001101110101001001100011 '
b1001001101110101001001100011 *
b1001001101110101001001100011 ,
b111 -
b10000 $
b101000001100101100 )
b110010110000101000010001101111 %
#17
b11111111111111111111100000000110 !
b11111111111111111111100000000110 (
b10000000111100111110001100100011 "
b10000000111100111110001100100011 '
b10000000111100111110001100100011 *
b10000000111100111110001100100011 ,
b1000 -
b10001 $
b10000100 )
b1100011 &
b1001001101110101001001100011 %
#18
b11111111111111111111100001101101 !
b11111111111111111111100001101101 (
b10000110110101111100110100000011 "
b10000110110101111100110100000011 '
b10000110110101111100110100000011 *
b10000110110101111100110100000011 ,
b1001 -
b10010 $
b11111111111111111111100000000110 )
b100011 &
b10000000111100111110001100100011 %
#19
b11111111111111111111101110110010 !
b11111111111111111111101110110010 (
b10111011001000111111000100010011 "
b10111011001000111111000100010011 '
b10111011001000111111000100010011 *
b10111011001000111111000100010011 ,
b1010 -
b10011 $
b11111111111111111111100001101101 )
b11 &
b10000110110101111100110100000011 %
#20
b11111111111111011100000111101000 !
b11111111111111011100000111101000 (
b10011110100011011100110101101111 "
b10011110100011011100110101101111 '
b10011110100011011100110101101111 *
b10011110100011011100110101101111 ,
b1011 -
b10100 $
b11111111111111111111101110110010 )
b10011 &
b10111011001000111111000100010011 %
#21
b11111111111111111111111101101111 !
b11111111111111111111111101101111 (
b11110110110101000101011110100011 "
b11110110110101000101011110100011 '
b11110110110101000101011110100011 *
b11110110110101000101011110100011 ,
b1100 -
b10101 $
b11111111111111011100000111101000 )
b1101111 &
b10011110100011011100110101101111 %
#22
b11111111111111111111110001101110 !
b11111111111111111111110001101110 (
b11000110001011011111011111100011 "
b11000110001011011111011111100011 '
b11000110001011011111011111100011 *
b11000110001011011111011111100011 ,
b1101 -
b10110 $
b11111111111111111111111101101111 )
b100011 &
b11110110110101000101011110100011 %
#23
b11111111111111111111111111001111 !
b11111111111111111111111111001111 (
b11111100111111011110100110000011 "
b11111100111111011110100110000011 '
b11111100111111011110100110000011 *
b11111100111111011110100110000011 ,
b1110 -
b10111 $
b11111111111111111111110001101110 )
b1100011 &
b11000110001011011111011111100011 %
#24
b11000110011 !
b11000110011 (
b1100011001101110010010010010011 "
b1100011001101110010010010010011 '
b1100011001101110010010010010011 *
b1100011001101110010010010010011 ,
b1111 -
b11000 $
b11111111111111111111111111001111 )
b11 &
b11111100111111011110100110000011 %
#25
b11000101111 !
b11000101111 (
b1100010111101111000010010000011 "
b1100010111101111000010010000011 '
b1100010111101111000010010000011 *
b1100010111101111000010010000011 ,
b10000 -
b11001 $
b11000110011 )
b10011 &
b1100011001101110010010010010011 %
#26
b10101010001 !
b10101010001 (
b1010101000100111101001010010011 "
b1010101000100111101001010010011 '
b1010101000100111101001010010011 *
b1010101000100111101001010010011 ,
b10001 -
b11010 $
b11000101111 )
b11 &
b1100010111101111000010010000011 %
#27
b11111111111111111111111100101111 !
b11111111111111111111111100101111 (
b11110010101011111111011110100011 "
b11110010101011111111011110100011 '
b11110010101011111111011110100011 *
b11110010101011111111011110100011 ,
b10010 -
b11011 $
b10101010001 )
b10011 &
b1010101000100111101001010010011 %
#28
b1110100100 !
b1110100100 (
b111011110100100111001000100011 "
b111011110100100111001000100011 '
b111011110100100111001000100011 *
b111011110100100111001000100011 ,
b10011 -
b11100 $
b11111111111111111111111100101111 )
b100011 &
b11110010101011111111011110100011 %
#29
b10010011 !
b10010011 (
b1001001100101101011001100111 "
b1001001100101101011001100111 '
b1001001100101101011001100111 *
b1001001100101101011001100111 ,
b10100 -
b11101 $
b1110100100 )
b111011110100100111001000100011 %
#30
b11111111111111111111110001110111 !
b11111111111111111111110001110111 (
b11000111111011001101101110100011 "
b11000111111011001101101110100011 '
b11000111111011001101101110100011 *
b11000111111011001101101110100011 ,
b10101 -
b11110 $
b10010011 )
b1100111 &
b1001001100101101011001100111 %
#31
b11111111111111111111111110010011 !
b11111111111111111111111110010011 (
b11111001001100000110100110010011 "
b11111001001100000110100110010011 '
b11111001001100000110100110010011 *
b11111001001100000110100110010011 ,
b10110 -
b11111 $
b11111111111111111111110001110111 )
b100011 &
b11000111111011001101101110100011 %
#32
b11001110111 !
b11001110111 (
b1100111011101101001011010010011 "
b1100111011101101001011010010011 '
b1100111011101101001011010010011 *
b1100111011101101001011010010011 ,
b10111 -
b100000 $
b11111111111111111111111110010011 )
b10011 &
b11111001001100000110100110010011 %
#33
b111101010100 !
b111101010100 (
b1110100000000000111101011100011 "
b1110100000000000111101011100011 '
b1110100000000000111101011100011 *
b1110100000000000111101011100011 ,
b11000 -
b100001 $
b11001110111 )
b1100111011101101001011010010011 %
#34
b11000101100 !
b11000101100 (
b1100010110010100100111010000011 "
b1100010110010100100111010000011 '
b1100010110010100100111010000011 *
b1100010110010100100111010000011 ,
b11001 -
b100010 $
b111101010100 )
b1100011 &
b1110100000000000111101011100011 %
#35
b11111111111111111111101011100101 !
b11111111111111111111101011100101 (
b10101110010110000100100101100111 "
b10101110010110000100100101100111 '
b10101110010110000100100101100111 *
b10101110010110000100100101100111 ,
b11010 -
b100011 $
b11000101100 )
b11 &
b1100010110010100100111010000011 %
#36
b11100010010111101000 !
b11100010010111101000 (
b1011110100011100010100011101111 "
b1011110100011100010100011101111 '
b1011110100011100010100011101111 *
b1011110100011100010100011101111 ,
b11011 -
b100100 $
b11111111111111111111101011100101 )
b1100111 &
b10101110010110000100100101100111 %
#37
b101101010 !
b101101010 (
b10110101010110101100000000011 "
b10110101010110101100000000011 '
b10110101010110101100000000011 *
b10110101010110101100000000011 ,
b11100 -
b100101 $
b11100010010111101000 )
b1101111 &
b1011110100011100010100011101111 %
#38
b1100101010 !
b1100101010 (
b110010101001110010011000000011 "
b110010101001110010011000000011 '
b110010101001110010011000000011 *
b110010101001110010011000000011 ,
b11101 -
b100110 $
b101101010 )
b11 &
b10110101010110101100000000011 %
#39
b1100011110 !
b1100011110 (
b110001111011110110001000000011 "
b110001111011110110001000000011 '
b110001111011110110001000000011 *
b110001111011110110001000000011 ,
b11110 -
b100111 $
b1100101010 )
b110010101001110010011000000011 %
#40
b11111111111111111111000001001110 !
b11111111111111111111000001001110 (
b10000101011100111000011101100011 "
b10000101011100111000011101100011 '
b10000101011100111000011101100011 *
b10000101011100111000011101100011 ,
b11111 -
b101000 $
b1100011110 )
b110001111011110110001000000011 %
#41
b10000000011 !
b10000000011 (
b1000000001110110010001011100111 "
b1000000001110110010001011100111 '
b1000000001110110010001011100111 *
b1000000001110110010001011100111 ,
b100000 -
b101001 $
b11111111111111111111000001001110 )
b1100011 &
b10000101011100111000011101100011 %
#42
b11111111111111111111000100000010 !
b11111111111111111111000100000010 (
b10010000011001000010000101100011 "
b10010000011001000010000101100011 '
b10010000011001000010000101100011 *
b10010000011001000010000101100011 ,
b100001 -
b101010 $
b10000000011 )
b1100111 &
b1000000001110110010001011100111 %
#43
b11111111111111111111110101010111 !
b11111111111111111111110101010111 (
b11010101011110000100010110010011 "
b11010101011110000100010110010011 '
b11010101011110000100010110010011 *
b11010101011110000100010110010011 ,
b100010 -
b101011 $
b11111111111111111111000100000010 )
b1100011 &
b10010000011001000010000101100011 %
#44
b10011111001 !
b10011111001 (
b1001110110011001100110010100011 "
b1001110110011001100110010100011 '
b1001110110011001100110010100011 *
b1001110110011001100110010100011 ,
b100011 -
b101100 $
b11111111111111111111110101010111 )
b10011 &
b11010101011110000100010110010011 %
#45
b10010110010 !
b10010110010 (
b1001011001000000011111010010011 "
b1001011001000000011111010010011 '
b1001011001000000011111010010011 *
b1001011001000000011111010010011 ,
b100100 -
b101101 $
b10011111001 )
b100011 &
b1001110110011001100110010100011 %
#46
b10010000 !
b10010000 (
b1001100000111011100000100011 "
b1001100000111011100000100011 '
b1001100000111011100000100011 *
b1001100000111011100000100011 ,
b100101 -
b101110 $
b10010110010 )
b10011 &
b1001011001000000011111010010011 %
#47
b1101011 !
b1101011 (
b110101111000011100000000011 "
b110101111000011100000000011 '
b110101111000011100000000011 *
b110101111000011100000000011 ,
b100110 -
b101111 $
b10010000 )
b100011 &
b1001100000111011100000100011 %
#48
b1010001100 !
b1010001100 (
b101001101001111101011000100011 "
b101001101001111101011000100011 '
b101001101001111101011000100011 *
b101001101001111101011000100011 ,
b100111 -
b110000 $
b1101011 )
b11 &
b110101111000011100000000011 %
#49
b101000 -
b110001 $
b1010001100 )
b100011 &
b101001101001111101011000100011 %
