DESIGN/RTL/mux/iord_mux.v
/*
==============================================================================
 Project      : RV32I Multi-Cycle RISC-V Processor
 Module No    : M13
 Module Name  : iord_mux
 File Name    : iord_mux.v

 Core         : RV32I
 Architecture : Multi-Cycle
 ISA          : RV32I Base Integer ISA
 XLEN         : 32-bit

 Description  : Selects the address supplied to the Unified Memory.


 Date Created : 06.07.2026
 Version      :

 Inputs       : pc, alu_out, IorD

 Outputs      : address

==============================================================================
*/

module iord_mux(pc, alu_out, IorD, address);
	
	input [31:0] pc, alu_out;
	input IorD;
	
	output [31:0] address;
	
	assign address = (IorD) ? alu_out : pc;
 
endmodule

DESIGN/TEST_BENCH/mux_tb/iord_mux_tb.v
module iord_mux_tb;

	reg [31:0] pc,alu_out;
	reg IorD;
	
	wire [31:0] address;
	
	iord_mux uut (pc, alu_out, IorD, address);
	integer seed = 100;
	integer seed1 = 200;
	
	task stimulus ;
	begin
		repeat(20)
		begin
            #10;
			pc       = $urandom(seed) ;
			alu_out  = $urandom(seed1);
			IorD     = $urandom %2;
            #1;
			
			$display("-----------------------");
			$display("pc == %0d",pc);
			$display("alu_out == %0d",alu_out);
            $display("IorD == %0d",IorD);
			#1;
		   if(address !== (IorD ? alu_out : pc))
			begin
                $display("address == %0d",address);
				$display("FAILED");
				$stop;
			end
			else
			begin
                $display("address == %0d",address);
				$display("PASSED");
			end
			
		end
	end
    endtask
	
	initial
	begin
		pc = 0;
		alu_out =2;
		IorD =0;
        #1;
             $display("-----------------------");
			 $display("pc == %0d",pc);
			 $display("alu_out == %0d",alu_out);
             $display("IorD == %0d",IorD);
            if(address !== (IorD ? alu_out : pc))
			begin
				$display("FAILED");
				$stop;
			end
			else
			begin
				$display("PASSED");
			end

		stimulus;
		#10;
        $finish;

	end

	initial begin
		$dumpfile("SIM/iord_mux.vcd");
		$dumpvars(0,iord_mux_tb);
	end
endmodule

DESIGN/SIM/iord_mux.vcd
$date
	Mon Jul 13 18:18:29 2026
$end
$version
	Icarus Verilog
$end
$timescale
	1s
$end
$scope module iord_mux_tb $end
$var wire 32 ! address [31:0] $end
$var reg 1 " IorD $end
$var reg 32 # alu_out [31:0] $end
$var reg 32 $ pc [31:0] $end
$var integer 32 % seed [31:0] $end
$var integer 32 & seed1 [31:0] $end
$scope module uut $end
$var wire 1 " IorD $end
$var wire 32 ' alu_out [31:0] $end
$var wire 32 ( pc [31:0] $end
$var wire 32 ) address [31:0] $end
$upscope $end
$scope task stimulus $end
$upscope $end
$upscope $end
$enddefinitions $end
$comment Show the parameter values. $end
$dumpall
$end
#0
$dumpvars
b0 )
b0 (
b10 '
b11001000 &
b1100100 %
b0 $
b10 #
0"
b0 !
$end
#11
b11010010110011000000000 !
b11010010110011000000000 )
b110100101100101000000001 #
b110100101100101000000001 '
b110100101100100000101001 &
b11010010110011000000000 $
b11010010110011000000000 (
b11010010110010000010101 %
#23
b10010100011110011011000100101 !
b10010100011110011011000100101 )
b100101000111010101111001001010 #
b100101000111010101111001001010 '
b100101000111010101110111010110 &
b10010100011110011011000100101 $
b10010100011110011011000100101 (
b10010100011110011010111010010 %
#35
b10010100000111100000010100101000 !
b10010100000111100000010100101000 )
1"
b10010100000111100000010100101000 #
b10010100000111100000010100101000 '
b10010100000111100000001001011111 &
b1011000001110111100010010110000 $
b1011000001110111100010010110000 (
b1011000001110111100001100101011 %
#47
b100100100001011011101001001001 !
b100100100001011011101001001001 )
b100100100001011011101001001001 #
b100100100001011011101001001001 '
b100100100001011011100100010100 &
b1110011111011110111101011100111 $
b1110011111011110111101011100111 (
b1110011111011110111100001110000 %
#59
b11000010100011110011101110000101 !
b11000010100011110011101110000101 )
b11000010100011110011101110000101 #
b11000010100011110011101110000101 '
b11000010100011110011100100000101 &
b1111000010100010010001011110000 $
b1111000010100010010001011110000 (
b1111000010100010010000110110001 %
#71
b1001011100110101110110010010111 !
b1001011100110101110110010010111 )
b1001011100110101110110010010111 #
b1001011100110101110110010010111 '
b1001011100110101110101000000010 &
b10011001010111101111100100110010 $
b10011001010111101111100100110010 (
b10011001010111101111011110111110 %
#83
b10011011010111110000101100110110 !
b10011011010111110000101100110110 )
0"
b1010010111100010111111010100101 #
b1010010111100010111111010100101 '
b1010010111100010111110110011011 &
b10011011010111110000101100110110 $
b10011011010111110000101100110110 (
b10011011010111110000100100100111 %
#95
b101100010111010111011001011000 !
b101100010111010111011001011000 )
1"
b101100010111010111011001011000 #
b101100010111010111011001011000 '
b101100010111010111010000100000 &
b1000111101110000101000010001111 $
b1000111101110000101000010001111 (
b1000111101110000100111100111100 %
#107
b11001110110011000000000110011 !
b11001110110011000000000110011 )
0"
b10111001110110111001111101110011 #
b10111001110110111001111101110011 '
b10111001110110111001110110100001 &
b11001110110011000000000110011 $
b11001110110011000000000110011 (
b11001110110010111111100001101 %
#119
b111101101010110110100001111011 !
b111101101010110110100001111011 )
b10011001011111110110100100110010 #
b10011001011111110110100100110010 '
b10011001011111110110011011101110 &
b111101101010110110100001111011 $
b111101101010110110100001111011 (
b111101101010110110011001101010 %
#131
b11001010001011011000010110010100 !
b11001010001011011000010110010100 )
1"
b11001010001011011000010110010100 #
b11001010001011011000010110010100 '
b11001010001011011000001010010111 &
b1111100110111100110011011111001 $
b1111100110111100110011011111001 (
b1111100110111100110010011100011 %
#143
b10101110000110010101001101011100 !
b10101110000110010101001101011100 )
0"
b10111000101010100011111101110001 #
b10111000101010100011111101110001 '
b10111000101010100011110111101100 &
b10101110000110010101001101011100 $
b10101110000110010101001101011100 (
b10101110000110010101000011001000 %
#155
b11000011011001001001001110000110 !
b11000011011001001001001110000110 )
1"
b11000011011001001001001110000110 #
b11000011011001001001001110000110 '
b11000011011001001001000111111101 &
b100001001111101101000001000 $
b100001001111101101000001000 (
b100001001111101100000101001 %
#167
b110010000010110010111001100100 !
b110010000010110010111001100100 )
0"
b100100111011111100001001001001 #
b100100111011111100001001001001 '
b100100111011111100000010011010 &
b110010000010110010111001100100 $
b110010000010110010111001100100 (
b110010000010110010110111010110 %
#179
b11010010000111011001010110100100 !
b11010010000111011001010110100100 )
b10000001010111110000111100000010 #
b10000001010111110000111100000010 '
b10000001010111110000110101010011 &
b11010010000111011001010110100100 $
b11010010000111011001010110100100 (
b11010010000111011001001001011111 %
#191
b1111010000111011110010011110100 !
b1111010000111011110010011110100 )
1"
b1111010000111011110010011110100 #
b1111010000111011110010011110100 '
b1111010000111011110001001111000 &
b1010100011111000000101010101000 $
b1010100011111000000101010101000 (
b1010100011111000000100100010100 %
#203
b11111100110111010100101111111001 !
b11111100110111010100101111111001 )
0"
b110000111001100111010001100001 #
b110000111001100111010001100001 '
b110000111001100111001000011001 &
b11111100110111010100101111111001 $
b11111100110111010100101111111001 (
b11111100110111010100100100000101 %
#215
b10111011011011110000000101 !
b10111011011011110000000101 )
b1001110011011011010010010011100 #
b1001110011011011010010010011100 '
b1001110011011011010001100000110 &
b10111011011011110000000101 $
b10111011011011110000000101 (
b10111011011011101000000010 %
#227
b10000110001101101000000100 !
b10000110001101101000000100 )
1"
b10000110001101101000000100 #
b10000110001101101000000100 '
b10000110001101100111001111 &
b100100110100100000111001001001 $
b100100110100100000111001001001 (
b100100110100100000110110011011 %
#239
b11001010110001001110111110010101 !
b11001010110001001110111110010101 )
b11001010110001001110111110010101 #
b11001010110001001110111110010101 '
b11001010110001001110110111000100 &
b110100100000001100011001101001 $
b110100100000001100011001101001 (
b110100100000001100010000100000 %
