DESIGN/RTL/datapath/pc.v
/*
==============================================================================
 Project      : RV32I Multi-Cycle RISC-V Processor
 Module No    : M1
 Module Name  : pc
 File Name    : pc.v

 Core         : RV32I
 Architecture : Multi-Cycle
 ISA          : RV32I Base Integer ISA
 XLEN         : 32-bit

 Description  : It provides the address to the Unified Memory during the Instruction Fetch (IF) cycle and is updated with the 
				address of the next instruction at the end of the cycle.

 Date Created : 07.07.2026
 Version      :

 Inputs       : clk, reset, pc_write_enb, pc_next

 Outputs      : pc

==============================================================================
*/

module pc(clk, reset, pc_write_enb, pc_next, pc);

	input clk, reset, pc_write_enb;
	input [31:0] pc_next;
	
	output reg [31:0] pc;
	
	always @(posedge clk or negedge reset)
		begin 
			if(!reset) pc <= 32'b00;
			else if(pc_write_enb) pc <= pc_next;
			else pc <= pc;
		end 
	

endmodule

DESIGN/TEST_BENCH/datapath_tb/pc_tb.v
module pc_tb;
	reg clk,reset,pc_write_enb;
	reg [31:0] pc_next;
	wire [31:0] pc;
	integer error_count;
	
	pc uut (clk,reset,pc_write_enb,pc_next,pc);
	
	initial begin
		clk = 0;
		forever #5 clk = ~clk;
	end
	
		
	
	task reset_logic;
		begin
			@(negedge clk )
			reset = 0;
			pc_next = 0;
			pc_write_enb =0;
			@(posedge clk)
			#1;
			if(pc == 32'd0)
			$display("pc is reseting");
			else
			begin
			$display("pc not is reseting");
			error_count = error_count +1;
			end
			
			@(negedge clk )
			reset = 1;
		end
	endtask
	
	
	
	task stimulus;
	reg [31:0] pc_pre;
		begin
		repeat(20)
		begin
			@(negedge clk )
			pc_write_enb = $random;
			pc_pre = pc;
			pc_next = pc_next +3'd4;
			@(posedge clk)
			#1;
			if(pc_write_enb)
			begin
				if(pc == pc_next)
				begin
					$display("pc is incrementing");
					$display("passed");
				end
				else
				begin
					$display("failed at expected pc_next = %0h",pc_next);
					error_count = error_count +1;
				end
			end
			else
			begin
				if(pc == pc_pre)
				$display(" pc is stay in old state");
				else
				begin
					$display("pc is not stay in old state");
					error_count = error_count+1;
				end
			end
		end
	end
	endtask
	
	initial begin
		error_count =0;
		reset_logic;
		stimulus;
	    if(error_count == 0)
		$display("all passed");
		else
		$display("failed with error = %0d",error_count);
		
		$finish;
	end
	
	initial begin
		$dumpfile("SIM/pc.vcd");
		$dumpvars(0,pc_tb);
	end
endmodule

DESIGN/SIM/pc.vcd
$date
	Tue Jul 21 22:42:35 2026
$end
$version
	Icarus Verilog
$end
$timescale
	1s
$end
$scope module pc_tb $end
$var wire 32 ! pc [31:0] $end
$var reg 1 " clk $end
$var reg 32 # pc_next [31:0] $end
$var reg 1 $ pc_write_enb $end
$var reg 1 % reset $end
$var integer 32 & error_count [31:0] $end
$scope module uut $end
$var wire 1 " clk $end
$var wire 32 ' pc_next [31:0] $end
$var wire 1 $ pc_write_enb $end
$var wire 1 % reset $end
$var reg 32 ( pc [31:0] $end
$upscope $end
$scope task reset_logic $end
$upscope $end
$scope task stimulus $end
$var reg 32 ) pc_pre [31:0] $end
$upscope $end
$upscope $end
$enddefinitions $end
$comment Show the parameter values. $end
$dumpall
$end
#0
$dumpvars
bx )
bx (
bx '
b0 &
x%
x$
bx #
0"
bx !
$end
#5
1"
#10
b0 !
b0 (
0$
b0 #
b0 '
0%
0"
#15
1"
#20
1%
0"
#25
1"
#30
b100 #
b100 '
b0 )
0"
#35
1"
#40
b1000 #
b1000 '
1$
0"
#45
b1000 !
b1000 (
1"
#50
b1100 #
b1100 '
b1000 )
0"
#55
b1100 !
b1100 (
1"
#60
b10000 #
b10000 '
b1100 )
0"
#65
b10000 !
b10000 (
1"
#70
b10100 #
b10100 '
b10000 )
0"
#75
b10100 !
b10100 (
1"
#80
b11000 #
b11000 '
b10100 )
0"
#85
b11000 !
b11000 (
1"
#90
b11100 #
b11100 '
b11000 )
0"
#95
b11100 !
b11100 (
1"
#100
b100000 #
b100000 '
b11100 )
0$
0"
#105
1"
#110
b100100 #
b100100 '
1$
0"
#115
b100100 !
b100100 (
1"
#120
b101000 #
b101000 '
b100100 )
0"
#125
b101000 !
b101000 (
1"
#130
b101100 #
b101100 '
b101000 )
0$
0"
#135
1"
#140
b110000 #
b110000 '
1$
0"
#145
b110000 !
b110000 (
1"
#150
b110100 #
b110100 '
b110000 )
0"
#155
b110100 !
b110100 (
1"
#160
b111000 #
b111000 '
b110100 )
0$
0"
#165
1"
#170
b111100 #
b111100 '
1$
0"
#175
b111100 !
b111100 (
1"
#180
b1000000 #
b1000000 '
b111100 )
0$
0"
#185
1"
#190
b1000100 #
b1000100 '
1$
0"
#195
b1000100 !
b1000100 (
1"
#200
b1001000 #
b1001000 '
b1000100 )
0$
0"
#205
1"
#210
b1001100 #
b1001100 '
1$
0"
#215
b1001100 !
b1001100 (
1"
#220
b1010000 #
b1010000 '
b1001100 )
0"
#225
b1010000 !
b1010000 (
1"
